config.json.example
gsapp.py
setup.py
gsapp.egg-info/PKG-INFO
gsapp.egg-info/SOURCES.txt
gsapp.egg-info/dependency_links.txt
gsapp.egg-info/top_level.txt