Metadata-Version: 1.1
Name: gsapp
Version: 0.1.2
Summary: gamescience python simple gsapp framework 
Home-page: https://github.com/jj4jj/gsapp
Author: jj4jj
Author-email: resc@vip.qq.com
License: MIT License
Keywords: app framework
Platform: UNKNOWN
Requires: tornado
